peekalink/__init__.py
peekalink/client.py
peekalink/errors.py
peekalink/http.py
peekalink/apis/__init__.py
peekalink/apis/is_available.py
peekalink/apis/link_preview.py
peekalink/models/__init__.py
peekalink/models/link_preview.py
peekalink/models/helpers/content_type.py
peekalink/models/helpers/image_asset.py
peekalink/models/helpers/link_details.py
peekalink-1.0.1.dist-info/LICENSE
peekalink-1.0.1.dist-info/METADATA
peekalink-1.0.1.dist-info/WHEEL
peekalink-1.0.1.dist-info/top_level.txt
peekalink-1.0.1.dist-info/RECORD
