Metadata-Version: 2.1
Name: peekalink
Version: 1.0.1
Summary: A Peekalink API wrapper for Python
Home-page: https://github.com/jozsefsallai/peekalink.py
Author: József Sallai
Author-email: jozsef@sallai.me
License: UNKNOWN
Project-URL: Bug Tracker, https://github.com/jozsefsallai/peekalink.py/issues
Platform: UNKNOWN
Classifier: Programming Language :: Python :: 3
Classifier: License :: OSI Approved :: MIT License
Classifier: Operating System :: OS Independent
Classifier: Intended Audience :: Developers
Classifier: Topic :: Internet
Classifier: Topic :: Software Development :: Libraries
Classifier: Topic :: Utilities
Requires-Python: >=3.7.0
Requires-Dist: python-dateutil (==2.8.1)
Requires-Dist: requests (>=2.5.4)
